{
  "category": "Beach Photos",
  "theme": "beach",
  "category_id": "beach_photos",
  "audiences": {
    "kids_4_under": [
      {
        "clue": "What time of day is called the 'Golden Hour' for taking beautiful photos?",
        "correctQuestion": "Early morning or late afternoon/early evening",
        "value": 200
      },
      {
        "clue": "What feature on your camera or phone helps you frame a perfect beach shot using a grid?",
        "correctQuestion": "Grid lines or rule of thirds",
        "value": 200
      },
      {
        "clue": "What is the name of the unwanted shine or reflection that sometimes appears on faces in photos?",
        "correctQuestion": "Glare or shine",
        "value": 200
      },
      {
        "clue": "What photography technique involves positioning the sun at the edge of frame during sunset at the beach?",
        "correctQuestion": "Backlighting",
        "value": 200
      },
      {
        "clue": "What is the term for the distance between the camera lens and the subject being photographed?",
        "correctQuestion": "Focal length",
        "value": 200
      },
      {
        "clue": "What is the degree of brightness and darkness in a photograph called, involving proper metering?",
        "correctQuestion": "Exposure",
        "value": 200
      },
      {
        "clue": "What white, grainy material covers most beaches?",
        "correctQuestion": "Sand",
        "value": 200
      },
      {
        "clue": "What large body of salt water surrounds beaches?",
        "correctQuestion": "Ocean",
        "value": 200
      },
      {
        "clue": "What are the tall structures built to break up waves and protect beaches called?",
        "correctQuestion": "Breakwaters or jetties",
        "value": 200
      },
      {
        "clue": "What weather phenomenon creates a beautiful sky display over water at the beach?",
        "correctQuestion": "Sunset",
        "value": 200
      },
      {
        "clue": "What is the sandy ridge that extends from the beach into shallow water called?",
        "correctQuestion": "Sandbar",
        "value": 200
      },
      {
        "clue": "What is the narrow strip of sand connecting two larger landmasses called?",
        "correctQuestion": "Tombolo",
        "value": 200
      },
      {
        "clue": "What do families collect in buckets and bags at the beach?",
        "correctQuestion": "Seashells",
        "value": 200
      },
      {
        "clue": "What frozen treat do many people enjoy eating while at the beach?",
        "correctQuestion": "Ice cream",
        "value": 200
      },
      {
        "clue": "What water sport involves riding waves on a board?",
        "correctQuestion": "Surfing",
        "value": 200
      },
      {
        "clue": "What building structure from 1873 in Atlantic City became iconic for beach photos?",
        "correctQuestion": "The boardwalk",
        "value": 200
      },
      {
        "clue": "What tradition involves building sculptures from sand on the beach?",
        "correctQuestion": "Sand sculpture or sand art",
        "value": 200
      },
      {
        "clue": "What is the study of shells and mollusks collected at the beach called?",
        "correctQuestion": "Conchology",
        "value": 200
      },
      {
        "clue": "What protective lotion prevents your skin from burning at the beach?",
        "correctQuestion": "Sunscreen or sunblock",
        "value": 200
      },
      {
        "clue": "What natural phenomenon makes the water look different colors - blue, green, or turquoise?",
        "correctQuestion": "Light reflection or water depth",
        "value": 200
      },
      {
        "clue": "What moving ocean pattern creates an interesting visual line in beach photos?",
        "correctQuestion": "Waves",
        "value": 200
      },
      {
        "clue": "What is the shimmering effect on water created by sunlight called?",
        "correctQuestion": "Sun glitter or sparkle",
        "value": 200
      },
      {
        "clue": "What optical illusion appears to hover over hot sand or water on a sunny day?",
        "correctQuestion": "Mirage",
        "value": 200
      },
      {
        "clue": "What is the rainbow-like effect seen in water droplets or ocean spray called?",
        "correctQuestion": "Iridescence",
        "value": 200
      },
      {
        "clue": "What sport do families play with a net and ball at the beach?",
        "correctQuestion": "Volleyball",
        "value": 200
      },
      {
        "clue": "What do children use to dig in the sand with a handle?",
        "correctQuestion": "Shovel or spade",
        "value": 200
      },
      {
        "clue": "What traditional game involves throwing a horseshoe-shaped object?",
        "correctQuestion": "Horseshoes",
        "value": 200
      },
      {
        "clue": "What activity involves lying on a lounger and getting tanned in the sun?",
        "correctQuestion": "Sunbathing",
        "value": 200
      },
      {
        "clue": "What competitive activity involves racing in the sand or water?",
        "correctQuestion": "Running or beach racing",
        "value": 200
      },
      {
        "clue": "What water activity involves propelling yourself through water using rhythmic arm and leg movements?",
        "correctQuestion": "Swimming",
        "value": 200
      },
      {
        "clue": "What device do you use to take photos of people at the beach?",
        "correctQuestion": "Camera or phone",
        "value": 200
      },
      {
        "clue": "What portable device most people now use to take vacation photos?",
        "correctQuestion": "Smartphone",
        "value": 200
      },
      {
        "clue": "What protective case keeps your camera safe from sand and water at the beach?",
        "correctQuestion": "Waterproof case or housing",
        "value": 200
      },
      {
        "clue": "What camera setting protects against the bright sand and water reflections?",
        "correctQuestion": "Exposure compensation or UV filter",
        "value": 200
      },
      {
        "clue": "What lens attachment extends your camera's ability to see distant subjects?",
        "correctQuestion": "Telephoto lens",
        "value": 200
      },
      {
        "clue": "What technology in cameras helps capture motion without blur in action shots?",
        "correctQuestion": "Fast shutter speed or continuous shooting mode",
        "value": 200
      }
    ],
    "kids_10_under": [],
    "teenagers": [],
    "adults": [],
    "no_humanity": []
  }
}